pylabview/LVblock.py
pylabview/LVclasses.py
pylabview/LVcode.py
pylabview/LVdatafill.py
pylabview/LVdatatype.py
pylabview/LVdatatyperef.py
pylabview/LVheap.py
pylabview/LVinstrument.py
pylabview/LVlinkinfo.py
pylabview/LVmisc.py
pylabview/LVparts.py
pylabview/LVrsrcontainer.py
pylabview/LVxml.py
pylabview/__init__.py
pylabview/modRSRC.py
pylabview/readRSRC.py
pylabview/assets/tom-thumb.pbm
pylabview/assets/tom-thumb.pil
pylabview/assets/tom-thumb.txt
pylabview-0.1.2.dist-info/METADATA
pylabview-0.1.2.dist-info/WHEEL
pylabview-0.1.2.dist-info/entry_points.txt
pylabview-0.1.2.dist-info/top_level.txt
pylabview-0.1.2.dist-info/RECORD
