Metadata-Version: 2.1
Name: pylabview
Version: 0.1.2
Summary: Python LabVIEW File Type Parser
Home-page: https://github.com/mefistotelis/pylabview
Author: mefistotelis
License: MIT
Project-URL: Bug Reports, https://github.com/mefistotelis/pylabview/issues
Project-URL: Source, https://github.com/mefistotelis/pylabview/
Keywords: labview vi instruments parser extractor reverse-engineering development
Platform: UNKNOWN
Classifier: Intended Audience :: Developers
Classifier: Programming Language :: Python
Classifier: Programming Language :: Python :: 3
Classifier: License :: OSI Approved :: MIT License
Classifier: Topic :: Utilities
Classifier: Topic :: Software Development
Requires-Python: >=3.4
Requires-Dist: Pillow
